zcatalyst_runtime_39/__init__.py
zcatalyst_runtime_39/init_handler.py
zcatalyst_runtime_39/log_formatter.py
zcatalyst_runtime_39/log_handler.py
zcatalyst_runtime_39/main.py
zcatalyst_runtime_39/meta.json
zcatalyst_runtime_39/requirements-prod.txt
zcatalyst_runtime_39/requirements.txt
zcatalyst_runtime_39/signal_handler.py
zcatalyst_runtime_39/flavours/__init__.py
zcatalyst_runtime_39/flavours/applogic.py
zcatalyst_runtime_39/flavours/basicio.py
zcatalyst_runtime_39/flavours/cron.py
zcatalyst_runtime_39/flavours/event.py
zcatalyst_runtime_39/flavours/integration.py
zcatalyst_runtime_39/flavours/job.py
zcatalyst_runtime_39/flavours/job_utils.py
zcatalyst_runtime_39/flavours/utils.py
zcatalyst_runtime_39-1.1.0.dist-info/LICENSE
zcatalyst_runtime_39-1.1.0.dist-info/METADATA
zcatalyst_runtime_39-1.1.0.dist-info/WHEEL
zcatalyst_runtime_39-1.1.0.dist-info/top_level.txt
zcatalyst_runtime_39-1.1.0.dist-info/RECORD
