Metadata-Version: 2.1
Name: zcatalyst_runtime_39
Version: 1.1.0
Summary: Catalyst runtime for Python 3.9-066c5e9c2b02ca257bcba2c6f576bd6227403933
Home-page: https://catalyst.zoho.com/
Author: Catalyst by Zoho
Author-email: support@zohocatalyst.com
Maintainer: Catalyst by Zoho
Maintainer-email: support@zohocatalyst.com
License: Apache 2.0
Keywords: zcatalyst,zoho,catalyst,serverless
Classifier: Programming Language :: Python :: 3 :: Only
Classifier: Programming Language :: Python :: 3.9
Classifier: License :: OSI Approved :: Apache Software License
Classifier: Development Status :: 4 - Beta
License-File: LICENSE
